Workbook

Sheet Business A
B3: Business Unit A: Financial Results
B5: Figures in USD
E7: 46142 | F7: =EOMONTH(E7,1) -> 46173 | G7: =EOMONTH(F7,1) -> 46203 | H7: =EOMONTH(G7,1) -> 46234 | J7: YTD Actual | K7: YTD Budget
B8: Income Statement
B9: Revenue | E9: 315000 | F9: 322000 | G9: 335000 | H9: 341000 | J9: =SUM(E9:H9) -> 1313000 | K9: 1300000
B10: Cost of Goods Sold | E10: -188000 | F10: -192000 | G10: -199000 | H10: -199000 | J10: =SUM(E10:H10) -> -778000 | K10: -770000
B11: Gross Profit | E11: =SUM(E9:E10) -> 127000 | F11: =SUM(F9:F10) -> 130000 | G11: =SUM(G9:G10) -> 136000 | H11: =SUM(H9:H10) -> 142000 | J11: =SUM(J9:J10) -> 535000 | K11: =SUM(K9:K10) -> 530000
B12: SG&A Expenses | E12: -77000 | F12: -79000 | G12: -81000 | H12: -81000 | J12: =SUM(E12:H12) -> -318000 | K12: -320000
B13: Net Income | E13: =SUM(E11:E12) -> 50000 | F13: =SUM(F11:F12) -> 51000 | G13: =SUM(G11:G12) -> 55000 | H13: =SUM(H11:H12) -> 61000 | J13: =SUM(J11:J12) -> 217000 | K13: =SUM(K11:K12) -> 210000
B15: Balance Sheet
B16: Cash Balance | E16: 110000 | F16: 130000 | G16: 160000 | H16: 196000 | J16: =H16 -> 196000 | K16: 190000
B17: Accounts Receivable | E17: 67000 | F17: 72000 | G17: 77000 | H17: 81000 | J17: =H17 -> 81000 | K17: 80000
B18: Accounts Payable | E18: 55000 | F18: 58000 | G18: 60000 | H18: 57000 | J18: =H18 -> 57000 | K18: 58000

Sheet Business B
B3: Business Unit B: Financial Results
B5: Figures in USD
E7: 46142 | F7: =EOMONTH(E7,1) -> 46173 | G7: =EOMONTH(F7,1) -> 46203 | H7: =EOMONTH(G7,1) -> 46234 | J7: YTD Actual | K7: YTD Budget
B8: Income Statement
B9: Revenue | E9: 540000 | F9: 555000 | G9: 575000 | H9: 585000 | J9: =SUM(E9:H9) -> 2255000 | K9: 2050000
B10: Cost of Goods Sold | E10: -298000 | F10: -305000 | G10: -315000 | H10: -322000 | J10: =SUM(E10:H10) -> -1240000 | K10: -1180000
B11: Gross Profit | E11: =SUM(E9:E10) -> 242000 | F11: =SUM(F9:F10) -> 250000 | G11: =SUM(G9:G10) -> 260000 | H11: =SUM(H9:H10) -> 263000 | J11: =SUM(J9:J10) -> 1015000 | K11: =SUM(K9:K10) -> 870000
B12: SG&A Expenses | E12: -113000 | F12: -115000 | G12: -118000 | H12: -119000 | J12: =SUM(E12:H12) -> -465000 | K12: -450000
B13: Net Income | E13: =SUM(E11:E12) -> 129000 | F13: =SUM(F11:F12) -> 135000 | G13: =SUM(G11:G12) -> 142000 | H13: =SUM(H11:H12) -> 144000 | J13: =SUM(J11:J12) -> 550000 | K13: =SUM(K11:K12) -> 420000
B15: Balance Sheet
B16: Cash Balance | E16: 170000 | F16: 190000 | G16: 210000 | H16: 232000 | J16: =H16 -> 232000 | K16: 200000
B17: Accounts Receivable | E17: 100000 | F17: 105000 | G17: 109000 | H17: 113000 | J17: =H17 -> 113000 | K17: 105000
B18: Accounts Payable | E18: 84000 | F18: 86000 | G18: 87000 | H18: 88000 | J18: =H18 -> 88000 | K18: 90000

Sheet Business C
B3: Business Unit C: Financial Results
B5: Figures in USD
E7: 46142 | F7: =EOMONTH(E7,1) -> 46173 | G7: =EOMONTH(F7,1) -> 46203 | H7: =EOMONTH(G7,1) -> 46234 | J7: YTD Actual | K7: YTD Budget
B8: Income Statement
B9: Revenue | E9: 165000 | F9: 170000 | G9: 176000 | H9: 179000 | J9: =SUM(E9:H9) -> 690000 | K9: 760000
B10: Cost of Goods Sold | E10: -119000 | F10: -122000 | G10: -126000 | H10: -128000 | J10: =SUM(E10:H10) -> -495000 | K10: -500000
B11: Gross Profit | E11: =SUM(E9:E10) -> 46000 | F11: =SUM(F9:F10) -> 48000 | G11: =SUM(G9:G10) -> 50000 | H11: =SUM(H9:H10) -> 51000 | J11: =SUM(J9:J10) -> 195000 | K11: =SUM(K9:K10) -> 260000
B12: SG&A Expenses | E12: -49000 | F12: -51000 | G12: -52000 | H12: -53000 | J12: =SUM(E12:H12) -> -205000 | K12: -185000
B13: Net Income | E13: =SUM(E11:E12) -> -3000 | F13: =SUM(F11:F12) -> -3000 | G13: =SUM(G11:G12) -> -2000 | H13: =SUM(H11:H12) -> -2000 | J13: =SUM(J11:J12) -> -10000 | K13: =SUM(K11:K12) -> 75000
B15: Balance Sheet
B16: Cash Balance | E16: 66000 | F16: 64000 | G16: 63000 | H16: 61000 | J16: =H16 -> 61000 | K16: 78000
B17: Accounts Receivable | E17: 40000 | F17: 39000 | G17: 37000 | H17: 35000 | J17: =H17 -> 35000 | K17: 42000
B18: Accounts Payable | E18: 33000 | F18: 36000 | G18: 38000 | H18: 41000 | J18: =H18 -> 41000 | K18: 35000

Sheet Group Consolidation
B3: Group Consolidation: Actual vs Budget
B5: Figures in USD
E7: 46142 | F7: =EOMONTH(E7,1) -> 46173 | G7: =EOMONTH(F7,1) -> 46203 | H7: =EOMONTH(G7,1) -> 46234 | J7: YTD Actual | K7: YTD Budget | M7: Variance $ | N7: Variance % | O7: F / U
B8: Income Statement
B9: Revenue | E9: ='Business A'!E9+'Business B'!E9+'Business C'!E9 -> 1020000 | F9: ='Business A'!F9+'Business B'!F9+'Business C'!F9 -> 1047000 | G9: ='Business A'!G9+'Business B'!G9+'Business C'!G9 -> 1086000 | H9: ='Business A'!H9+'Business B'!H9+'Business C'!H9 -> 1105000 | J9: ='Business A'!J9+'Business B'!J9+'Business C'!J9 -> 4258000 | K9: ='Business A'!K9+'Business B'!K9+'Business C'!K9 -> 4110000 | M9: =J9-K9 -> 148000 | N9: =M9/K9 -> 0.036009732 | O9: =IF(M9>=0,"Favorable","Unfavorable") -> Favorable
B10: Cost of Goods Sold | E10: ='Business A'!E10+'Business B'!E10+'Business C'!E10 -> -605000 | F10: ='Business A'!F10+'Business B'!F10+'Business C'!F10 -> -619000 | G10: ='Business A'!G10+'Business B'!G10+'Business C'!G10 -> -640000 | H10: ='Business A'!H10+'Business B'!H10+'Business C'!H10 -> -649000 | J10: ='Business A'!J10+'Business B'!J10+'Business C'!J10 -> -2513000 | K10: ='Business A'!K10+'Business B'!K10+'Business C'!K10 -> -2450000 | M10: =J10-K10 -> -63000 | N10: =M10/K10 -> 0.025714286 | O10: =IF(M10>=0,"Favorable","Unfavorable") -> Unfavorable
B11: Gross Profit | E11: =SUM(E9:E10) -> 415000 | F11: =SUM(F9:F10) -> 428000 | G11: =SUM(G9:G10) -> 446000 | H11: =SUM(H9:H10) -> 456000 | J11: =SUM(J9:J10) -> 1745000 | K11: =SUM(K9:K10) -> 1660000 | M11: =SUM(M9:M10) -> 85000 | N11: =M11/K11 -> 0.051204819 | O11: =IF(M11>0,"Favorable","Unfavorable") -> Favorable
B12: SG&A Expenses | E12: ='Business A'!E12+'Business B'!E12+'Business C'!E12 -> -239000 | F12: ='Business A'!F12+'Business B'!F12+'Business C'!F12 -> -245000 | G12: ='Business A'!G12+'Business B'!G12+'Business C'!G12 -> -251000 | H12: ='Business A'!H12+'Business B'!H12+'Business C'!H12 -> -253000 | J12: ='Business A'!J12+'Business B'!J12+'Business C'!J12 -> -988000 | K12: ='Business A'!K12+'Business B'!K12+'Business C'!K12 -> -955000 | M12: =J12-K12 -> -33000 | N12: =M12/K12 -> 0.034554974 | O12: =IF(M12>=0,"Favorable","Unfavorable") -> Unfavorable
B13: Net Income | E13: =SUM(E11:E12) -> 176000 | F13: =SUM(F11:F12) -> 183000 | G13: =SUM(G11:G12) -> 195000 | H13: =SUM(H11:H12) -> 203000 | J13: =SUM(J11:J12) -> 757000 | K13: =SUM(K11:K12) -> 705000 | M13: =SUM(M11:M12) -> 52000 | N13: =M13/K13 -> 0.073758865 | O13: =IF(M13>0,"Favorable","Unfavorable") -> Favorable
B14: Balance Sheet
B15: Cash Balance | E15: ='Business A'!E16+'Business B'!E16+'Business C'!E16 -> 346000 | F15: ='Business A'!F16+'Business B'!F16+'Business C'!F16 -> 384000 | G15: ='Business A'!G16+'Business B'!G16+'Business C'!G16 -> 433000 | H15: ='Business A'!H16+'Business B'!H16+'Business C'!H16 -> 489000 | J15: =H15 -> 489000 | K15: ='Business A'!K16+'Business B'!K16+'Business C'!K16 -> 468000 | M15: =J15-K15 -> 21000 | N15: =M15/K15 -> 0.044871795 | O15: =IF(M15>0,"Favorable","Unfavorable") -> Favorable
B16: Accounts Receivable | E16: ='Business A'!E17+'Business B'!E17+'Business C'!E17 -> 207000 | F16: ='Business A'!F17+'Business B'!F17+'Business C'!F17 -> 216000 | G16: ='Business A'!G17+'Business B'!G17+'Business C'!G17 -> 223000 | H16: ='Business A'!H17+'Business B'!H17+'Business C'!H17 -> 229000 | J16: =H16 -> 229000 | K16: ='Business A'!K17+'Business B'!K17+'Business C'!K17 -> 227000 | M16: =J16-K16 -> 2000 | N16: =M16/K16 -> 0.0088105727 | O16: =IF(M16<=0,"Favorable","Unfavorable") -> Unfavorable
B17: Accounts Payable | E17: ='Business A'!E18+'Business B'!E18+'Business C'!E18 -> 172000 | F17: ='Business A'!F18+'Business B'!F18+'Business C'!F18 -> 180000 | G17: ='Business A'!G18+'Business B'!G18+'Business C'!G18 -> 185000 | H17: ='Business A'!H18+'Business B'!H18+'Business C'!H18 -> 186000 | J17: =H17 -> 186000 | K17: ='Business A'!K18+'Business B'!K18+'Business C'!K18 -> 183000 | M17: =J17-K17 -> 3000 | N17: =M17/K17 -> 0.016393443 | O17: =IF(M17>=0,"Favorable","Unfavorable") -> Favorable
B20: Variance Commentary
A21: # | B21: Net income of $757K beat budget ($705K) by $52K (+7.4%), as a $148K (+3.6%) revenue outperformance more than offset cost overruns.
A22: # | B22: Revenue and gross profit were favorable (+$148K / +$85K), but COGS (−$63K) and SG&A (−$33K) both ran over budget, the two lines to watch.
A23: # | B23: Business B (best case) drove the upside: revenue +10% and net income of $550K vs a $420K budget (+31%).
A24: # | B24: Business C (worst case) was the main drag: revenue missed by ~9% and it posted a $10K loss against a $75K budget on cost overruns.
A25: # | B25: Business A (base case) tracked plan: net income of $217K vs $210K (+3%); balance-sheet lines were broadly on budget.
A26: # | B26: Next steps: investigate the COGS and SG&A overruns (volume-driven by Business B's +10% revenue, or true cost inflation?), and review Business C's revenue shortfall and cost overruns given its swing to a loss.

Sheet Week 2 Forecast
B3: Week 2: Forecast to Full Year (FORECAST.ETS)
B5: Figures in USD | Apr–Jul = actuals, Aug–Mar = FORECAST.ETS projections
B7: Business A
B8: Month | C8: Revenue | D8: COGS | E8: Gross Profit | F8: SG&A | G8: Net Income
B9: 46142 | C9: {=TRANSPOSE('Business A'!E9:H9)} -> 315000 | D9: {=TRANSPOSE('Business A'!E10:H10)} -> -188000 | E9: =SUM(C9:D9) -> 127000 | F9: {=TRANSPOSE('Business A'!E12:H12)} -> -77000 | G9: =SUM(E9:F9) -> 50000
B10: =EDATE(B9,1) -> 46172 | C10: 322000 | D10: -192000 | E10: =SUM(C10:D10) -> 130000 | F10: -79000 | G10: =SUM(E10:F10) -> 51000
B11: =EDATE(B10,1) -> 46203 | C11: 335000 | D11: -199000 | E11: =SUM(C11:D11) -> 136000 | F11: -81000 | G11: =SUM(E11:F11) -> 55000
B12: =EDATE(B11,1) -> 46233 | C12: 341000 | D12: -199000 | E12: =SUM(C12:D12) -> 142000 | F12: -81000 | G12: =SUM(E12:F12) -> 61000
B13: =EDATE(B12,1) -> 46264 | C13: =_xlfn.FORECAST.ETS($B13,C$9:C$12,$B$9:$B$12,0) -> 351137.1 | D13: =_xlfn.FORECAST.ETS($B13,D$9:D$12,$B$9:$B$12,0) -> -203806.9 | E13: =SUM(C13:D13) -> 147330.2 | F13: =_xlfn.FORECAST.ETS($B13,F$9:F$12,$B$9:$B$12,0) -> -82745.126 | G13: =SUM(E13:F13) -> 64585.077
B14: =EDATE(B13,1) -> 46295 | C14: =_xlfn.FORECAST.ETS($B14,C$9:C$12,$B$9:$B$12,0) -> 360171.61 | D14: =_xlfn.FORECAST.ETS($B14,D$9:D$12,$B$9:$B$12,0) -> -207702.05 | E14: =SUM(C14:D14) -> 152469.56 | F14: =_xlfn.FORECAST.ETS($B14,F$9:F$12,$B$9:$B$12,0) -> -84103.521 | G14: =SUM(E14:F14) -> 68366.036
B15: =EDATE(B14,1) -> 46325 | C15: =_xlfn.FORECAST.ETS($B15,C$9:C$12,$B$9:$B$12,0) -> 369206.12 | D15: =_xlfn.FORECAST.ETS($B15,D$9:D$12,$B$9:$B$12,0) -> -211597.21 | E15: =SUM(C15:D15) -> 157608.91 | F15: =_xlfn.FORECAST.ETS($B15,F$9:F$12,$B$9:$B$12,0) -> -85461.915 | G15: =SUM(E15:F15) -> 72146.996
B16: =EDATE(B15,1) -> 46356 | C16: =_xlfn.FORECAST.ETS($B16,C$9:C$12,$B$9:$B$12,0) -> 378240.63 | D16: =_xlfn.FORECAST.ETS($B16,D$9:D$12,$B$9:$B$12,0) -> -215492.36 | E16: =SUM(C16:D16) -> 162748.26 | F16: =_xlfn.FORECAST.ETS($B16,F$9:F$12,$B$9:$B$12,0) -> -86820.309 | G16: =SUM(E16:F16) -> 75927.955
B17: =EDATE(B16,1) -> 46386 | C17: =_xlfn.FORECAST.ETS($B17,C$9:C$12,$B$9:$B$12,0) -> 387275.14 | D17: =_xlfn.FORECAST.ETS($B17,D$9:D$12,$B$9:$B$12,0) -> -219387.52 | E17: =SUM(C17:D17) -> 167887.62 | F17: =_xlfn.FORECAST.ETS($B17,F$9:F$12,$B$9:$B$12,0) -> -88178.704 | G17: =SUM(E17:F17) -> 79708.914
B18: =EDATE(B17,1) -> 46417 | C18: =_xlfn.FORECAST.ETS($B18,C$9:C$12,$B$9:$B$12,0) -> 396309.65 | D18: =_xlfn.FORECAST.ETS($B18,D$9:D$12,$B$9:$B$12,0) -> -223282.67 | E18: =SUM(C18:D18) -> 173026.97 | F18: =_xlfn.FORECAST.ETS($B18,F$9:F$12,$B$9:$B$12,0) -> -89537.098 | G18: =SUM(E18:F18) -> 83489.874
B19: =EDATE(B18,1) -> 46446 | C19: =_xlfn.FORECAST.ETS($B19,C$9:C$12,$B$9:$B$12,0) -> 404761.28 | D19: =_xlfn.FORECAST.ETS($B19,D$9:D$12,$B$9:$B$12,0) -> -226926.53 | E19: =SUM(C19:D19) -> 177834.75 | F19: =_xlfn.FORECAST.ETS($B19,F$9:F$12,$B$9:$B$12,0) -> -90807.854 | G19: =SUM(E19:F19) -> 87026.9
B20: =EDATE(B19,1) -> 46474 | C20: =_xlfn.FORECAST.ETS($B20,C$9:C$12,$B$9:$B$12,0) -> 413733.34 | D20: =_xlfn.FORECAST.ETS($B20,D$9:D$12,$B$9:$B$12,0) -> -230794.76 | E20: =SUM(C20:D20) -> 182938.58 | F20: =_xlfn.FORECAST.ETS($B20,F$9:F$12,$B$9:$B$12,0) -> -92156.859 | G20: =SUM(E20:F20) -> 90781.724
B21: FY Outlook | C21: =SUM(C9:C20) -> 4373834.9 | D21: =SUM(D9:D20) -> -2516990 | E21: =C21+D21 -> 1856844.9 | F21: =SUM(F9:F20) -> -1017811.4 | G21: =E21+F21 -> 839033.48
B23: FY Budget | C23: ='Business A'!K9*3 -> 3900000 | D23: ='Business A'!K10*3 -> -2310000 | E23: =C23+D23 -> 1590000 | F23: ='Business A'!K12*3 -> -960000 | G23: =E23+F23 -> 630000
B25: Variance $ | C25: =C21-C23 -> 473834.87 | D25: =D21-D23 -> -206990 | E25: =E21-E23 -> 266844.86 | F25: =F21-F23 -> -57811.386 | G25: =G21-G23 -> 209033.48
B27: Business B
B28: Month | C28: Revenue | D28: COGS | E28: Gross Profit | F28: SG&A | G28: Net Income
B29: =B9 -> 46142 | C29: {=TRANSPOSE('Business B'!E9:H9)} -> 540000 | D29: {=TRANSPOSE('Business B'!E10:H10)} -> -298000 | E29: =SUM(C29:D29) -> 242000 | F29: {=TRANSPOSE('Business B'!E12:H12)} -> -113000 | G29: =SUM(E29:F29) -> 129000
B30: =B10 -> 46172 | C30: 555000 | D30: -305000 | E30: =SUM(C30:D30) -> 250000 | F30: -115000 | G30: =SUM(E30:F30) -> 135000
B31: =B11 -> 46203 | C31: 575000 | D31: -315000 | E31: =SUM(C31:D31) -> 260000 | F31: -118000 | G31: =SUM(E31:F31) -> 142000
B32: =B12 -> 46233 | C32: 585000 | D32: -322000 | E32: =SUM(C32:D32) -> 263000 | F32: -119000 | G32: =SUM(E32:F32) -> 144000
B33: =B13 -> 46264 | C33: =_xlfn.FORECAST.ETS($B33,C$29:C$32,$B$29:$B$32,0) -> 601440.68 | D33: =_xlfn.FORECAST.ETS($B33,D$29:D$32,$B$29:$B$32,0) -> -330709.38 | E33: =SUM(C33:D33) -> 270731.3 | F33: =_xlfn.FORECAST.ETS($B33,F$29:F$32,$B$29:$B$32,0) -> -121288.14 | G33: =SUM(E33:F33) -> 149443.17
B34: =B14 -> 46295 | C34: =_xlfn.FORECAST.ETS($B34,C$29:C$32,$B$29:$B$32,0) -> 616800.67 | D34: =_xlfn.FORECAST.ETS($B34,D$29:D$32,$B$29:$B$32,0) -> -338886.89 | E34: =SUM(C34:D34) -> 277913.79 | F34: =_xlfn.FORECAST.ETS($B34,F$29:F$32,$B$29:$B$32,0) -> -123360.13 | G34: =SUM(E34:F34) -> 154553.65
B35: =B15 -> 46325 | C35: =_xlfn.FORECAST.ETS($B35,C$29:C$32,$B$29:$B$32,0) -> 632160.66 | D35: =_xlfn.FORECAST.ETS($B35,D$29:D$32,$B$29:$B$32,0) -> -347064.39 | E35: =SUM(C35:D35) -> 285096.27 | F35: =_xlfn.FORECAST.ETS($B35,F$29:F$32,$B$29:$B$32,0) -> -125432.13 | G35: =SUM(E35:F35) -> 159664.14
B36: =B16 -> 46356 | C36: =_xlfn.FORECAST.ETS($B36,C$29:C$32,$B$29:$B$32,0) -> 647520.65 | D36: =_xlfn.FORECAST.ETS($B36,D$29:D$32,$B$29:$B$32,0) -> -355241.9 | E36: =SUM(C36:D36) -> 292278.75 | F36: =_xlfn.FORECAST.ETS($B36,F$29:F$32,$B$29:$B$32,0) -> -127504.13 | G36: =SUM(E36:F36) -> 164774.62
B37: =B17 -> 46386 | C37: =_xlfn.FORECAST.ETS($B37,C$29:C$32,$B$29:$B$32,0) -> 662880.64 | D37: =_xlfn.FORECAST.ETS($B37,D$29:D$32,$B$29:$B$32,0) -> -363419.4 | E37: =SUM(C37:D37) -> 299461.24 | F37: =_xlfn.FORECAST.ETS($B37,F$29:F$32,$B$29:$B$32,0) -> -129576.13 | G37: =SUM(E37:F37) -> 169885.11
B38: =B18 -> 46417 | C38: =_xlfn.FORECAST.ETS($B38,C$29:C$32,$B$29:$B$32,0) -> 678240.63 | D38: =_xlfn.FORECAST.ETS($B38,D$29:D$32,$B$29:$B$32,0) -> -371596.91 | E38: =SUM(C38:D38) -> 306643.72 | F38: =_xlfn.FORECAST.ETS($B38,F$29:F$32,$B$29:$B$32,0) -> -131648.13 | G38: =SUM(E38:F38) -> 174995.59
B39: =B19 -> 46446 | C39: =_xlfn.FORECAST.ETS($B39,C$29:C$32,$B$29:$B$32,0) -> 692609.66 | D39: =_xlfn.FORECAST.ETS($B39,D$29:D$32,$B$29:$B$32,0) -> -379246.84 | E39: =SUM(C39:D39) -> 313362.82 | F39: =_xlfn.FORECAST.ETS($B39,F$29:F$32,$B$29:$B$32,0) -> -133586.45 | G39: =SUM(E39:F39) -> 179776.37
B40: =B20 -> 46474 | C40: =_xlfn.FORECAST.ETS($B40,C$29:C$32,$B$29:$B$32,0) -> 707863.47 | D40: =_xlfn.FORECAST.ETS($B40,D$29:D$32,$B$29:$B$32,0) -> -387367.82 | E40: =SUM(C40:D40) -> 320495.65 | F40: =_xlfn.FORECAST.ETS($B40,F$29:F$32,$B$29:$B$32,0) -> -135644.12 | G40: =SUM(E40:F40) -> 184851.53
B41: FY Outlook | C41: =SUM(C29:C40) -> 7494517.1 | D41: =SUM(D29:D40) -> -4113533.5 | E41: =C41+D41 -> 3380983.5 | F41: =SUM(F29:F40) -> -1493039.4 | G41: =E41+F41 -> 1887944.2
B43: FY Budget | C43: ='Business B'!K9*3 -> 6150000 | D43: ='Business B'!K10*3 -> -3540000 | E43: =C43+D43 -> 2610000 | F43: ='Business B'!K12*3 -> -1350000 | G43: =E43+F43 -> 1260000
B45: Variance $ | C45: =C41-C43 -> 1344517.1 | D45: =D41-D43 -> -573533.52 | E45: =E41-E43 -> 770983.55 | F45: =F41-F43 -> -143039.36 | G45: =G41-G43 -> 627944.19
B47: Business C
B48: Month | C48: Revenue | D48: COGS | E48: Gross Profit | F48: SG&A | G48: Net Income
B49: =B29 -> 46142 | C49: {=TRANSPOSE('Business C'!E9:H9)} -> 165000 | D49: {=TRANSPOSE('Business C'!E10:H10)} -> -119000 | E49: =SUM(C49:D49) -> 46000 | F49: {=TRANSPOSE('Business C'!E12:H12)} -> -49000 | G49: =SUM(E49:F49) -> -3000
B50: =B30 -> 46172 | C50: 170000 | D50: -122000 | E50: =SUM(C50:D50) -> 48000 | F50: -51000 | G50: =SUM(E50:F50) -> -3000
B51: =B31 -> 46203 | C51: 176000 | D51: -126000 | E51: =SUM(C51:D51) -> 50000 | F51: -52000 | G51: =SUM(E51:F51) -> -2000
B52: =B32 -> 46233 | C52: 179000 | D52: -128000 | E52: =SUM(C52:D52) -> 51000 | F52: -53000 | G52: =SUM(E52:F52) -> -2000
B53: =B33 -> 46264 | C53: =_xlfn.FORECAST.ETS($B53,C$49:C$52,$B$49:$B$52,0) -> 184160.69 | D53: =_xlfn.FORECAST.ETS($B53,D$49:D$52,$B$49:$B$52,0) -> -131288.14 | E53: =SUM(C53:D53) -> 52872.554 | F53: =_xlfn.FORECAST.ETS($B53,F$49:F$52,$B$49:$B$52,0) -> -54361.363 | G53: =SUM(E53:F53) -> -1488.8096
B54: =B34 -> 46295 | C54: =_xlfn.FORECAST.ETS($B54,C$49:C$52,$B$49:$B$52,0) -> 188911.94 | D54: =_xlfn.FORECAST.ETS($B54,D$49:D$52,$B$49:$B$52,0) -> -134360.13 | E54: =SUM(C54:D54) -> 54551.806 | F54: =_xlfn.FORECAST.ETS($B54,F$49:F$52,$B$49:$B$52,0) -> -55647.941 | G54: =SUM(E54:F54) -> -1096.1359
B55: =B35 -> 46325 | C55: =_xlfn.FORECAST.ETS($B55,C$49:C$52,$B$49:$B$52,0) -> 193663.19 | D55: =_xlfn.FORECAST.ETS($B55,D$49:D$52,$B$49:$B$52,0) -> -137432.13 | E55: =SUM(C55:D55) -> 56231.057 | F55: =_xlfn.FORECAST.ETS($B55,F$49:F$52,$B$49:$B$52,0) -> -56934.52 | G55: =SUM(E55:F55) -> -703.46216
B56: =B36 -> 46356 | C56: =_xlfn.FORECAST.ETS($B56,C$49:C$52,$B$49:$B$52,0) -> 198414.44 | D56: =_xlfn.FORECAST.ETS($B56,D$49:D$52,$B$49:$B$52,0) -> -140504.13 | E56: =SUM(C56:D56) -> 57910.309 | F56: =_xlfn.FORECAST.ETS($B56,F$49:F$52,$B$49:$B$52,0) -> -58221.098 | G56: =SUM(E56:F56) -> -310.78845
B57: =B37 -> 46386 | C57: =_xlfn.FORECAST.ETS($B57,C$49:C$52,$B$49:$B$52,0) -> 203165.69 | D57: =_xlfn.FORECAST.ETS($B57,D$49:D$52,$B$49:$B$52,0) -> -143576.13 | E57: =SUM(C57:D57) -> 59589.561 | F57: =_xlfn.FORECAST.ETS($B57,F$49:F$52,$B$49:$B$52,0) -> -59507.676 | G57: =SUM(E57:F57) -> 81.885261
B58: =B38 -> 46417 | C58: =_xlfn.FORECAST.ETS($B58,C$49:C$52,$B$49:$B$52,0) -> 207916.94 | D58: =_xlfn.FORECAST.ETS($B58,D$49:D$52,$B$49:$B$52,0) -> -146648.13 | E58: =SUM(C58:D58) -> 61268.813 | F58: =_xlfn.FORECAST.ETS($B58,F$49:F$52,$B$49:$B$52,0) -> -60794.254 | G58: =SUM(E58:F58) -> 474.55897
B59: =B39 -> 46446 | C59: =_xlfn.FORECAST.ETS($B59,C$49:C$52,$B$49:$B$52,0) -> 212361.66 | D59: =_xlfn.FORECAST.ETS($B59,D$49:D$52,$B$49:$B$52,0) -> -149521.93 | E59: =SUM(C59:D59) -> 62839.726 | F59: =_xlfn.FORECAST.ETS($B59,F$49:F$52,$B$49:$B$52,0) -> -61997.827 | G59: =SUM(E59:F59) -> 841.8989
B60: =B40 -> 46474 | C60: =_xlfn.FORECAST.ETS($B60,C$49:C$52,$B$49:$B$52,0) -> 217080.06 | D60: =_xlfn.FORECAST.ETS($B60,D$49:D$52,$B$49:$B$52,0) -> -152572.69 | E60: =SUM(C60:D60) -> 64507.37 | F60: =_xlfn.FORECAST.ETS($B60,F$49:F$52,$B$49:$B$52,0) -> -63275.512 | G60: =SUM(E60:F60) -> 1231.8583
B61: FY Outlook | C61: =SUM(C49:C60) -> 2295674.6 | D61: =SUM(D49:D60) -> -1630903.4 | E61: =C61+D61 -> 664771.2 | F61: =SUM(F49:F60) -> -675740.19 | G61: =E61+F61 -> -10968.995
B63: FY Budget | C63: ='Business C'!K9*3 -> 2280000 | D63: ='Business C'!K10*3 -> -1500000 | E63: =C63+D63 -> 780000 | F63: ='Business C'!K12*3 -> -555000 | G63: =E63+F63 -> 225000
B65: Variance $ | C65: =C61-C63 -> 15674.611 | D65: =D61-D63 -> -130903.41 | E65: =E61-E63 -> -115228.8 | F65: =F61-F63 -> -120740.19 | G65: =G61-G63 -> -235968.99
B67: Group
B68: Month | C68: Revenue | D68: COGS | E68: Gross Profit | F68: SG&A | G68: Net Income | H68: Rev Growth %
B69: =B49 -> 46142 | C69: =C9+C29+C49 -> 1020000 | D69: =D9+D29+D49 -> -605000 | E69: =C69+D69 -> 415000 | F69: =F9+F29+F49 -> -239000 | G69: =E69+F69 -> 176000
B70: =B50 -> 46172 | C70: =C10+C30+C50 -> 1047000 | D70: =D10+D30+D50 -> -619000 | E70: =C70+D70 -> 428000 | F70: =F10+F30+F50 -> -245000 | G70: =E70+F70 -> 183000 | H70: {=IFERROR(C70:C80/C69:C79-1,0)} -> 0.026470588
B71: =B51 -> 46203 | C71: =C11+C31+C51 -> 1086000 | D71: =D11+D31+D51 -> -640000 | E71: =C71+D71 -> 446000 | F71: =F11+F31+F51 -> -251000 | G71: =E71+F71 -> 195000 | H71: 0.037249284
B72: =B52 -> 46233 | C72: =C12+C32+C52 -> 1105000 | D72: =D12+D32+D52 -> -649000 | E72: =C72+D72 -> 456000 | F72: =F12+F32+F52 -> -253000 | G72: =E72+F72 -> 203000 | H72: 0.017495396
B73: =B53 -> 46264 | C73: =C13+C33+C53 -> 1136738.5 | D73: =D13+D33+D53 -> -665804.42 | E73: =C73+D73 -> 470934.06 | F73: =F13+F33+F53 -> -258394.63 | G73: =E73+F73 -> 212539.44 | H73: 0.028722604
B74: =B54 -> 46295 | C74: =C14+C34+C54 -> 1165884.2 | D74: =D14+D34+D54 -> -680949.08 | E74: =C74+D74 -> 484935.15 | F74: =F14+F34+F54 -> -263111.6 | G74: =E74+F74 -> 221823.55 | H74: 0.025639801
B75: =B55 -> 46325 | C75: =C15+C35+C55 -> 1195030 | D75: =D15+D35+D55 -> -696093.73 | E75: =C75+D75 -> 498936.24 | F75: =F15+F35+F55 -> -267828.57 | G75: =E75+F75 -> 231107.67 | H75: 0.024998835
B76: =B56 -> 46356 | C76: =C16+C36+C56 -> 1224175.7 | D76: =D16+D36+D56 -> -711238.39 | E76: =C76+D76 -> 512937.33 | F76: =F16+F36+F56 -> -272545.54 | G76: =E76+F76 -> 240391.79 | H76: 0.024389135
B77: =B57 -> 46386 | C77: =C17+C37+C57 -> 1253321.5 | D77: =D17+D37+D57 -> -726383.05 | E77: =C77+D77 -> 526938.42 | F77: =F17+F37+F57 -> -277262.51 | G77: =E77+F77 -> 249675.91 | H77: 0.023808467
B78: =B58 -> 46417 | C78: =C18+C38+C58 -> 1282467.2 | D78: =D18+D38+D58 -> -741527.71 | E78: =C78+D78 -> 540939.51 | F78: =F18+F38+F58 -> -281979.48 | G78: =E78+F78 -> 258960.03 | H78: 0.023254806
B79: =B59 -> 46446 | C79: =C19+C39+C59 -> 1309732.6 | D79: =D19+D39+D59 -> -755695.29 | E79: =C79+D79 -> 554037.3 | F79: =F19+F39+F59 -> -286392.13 | G79: =E79+F79 -> 267645.17 | H79: 0.021260097
B80: =B60 -> 46474 | C80: =C20+C40+C60 -> 1338676.9 | D80: =D20+D40+D60 -> -770735.27 | E80: =C80+D80 -> 567941.61 | F80: =F20+F40+F60 -> -291076.49 | G80: =E80+F80 -> 276865.11 | H80: 0.022099381
B81: FY Outlook | C81: =SUM(C69:C80) -> 14164027 | D81: =SUM(D69:D80) -> -8261426.9 | E81: =C81+D81 -> 5902599.6 | F81: =SUM(F69:F80) -> -3186590.9 | G81: =E81+F81 -> 2716008.7
B83: FY Budget | C83: =C23+C43+C63 -> 12330000 | D83: =D23+D43+D63 -> -7350000 | E83: =C83+D83 -> 4980000 | F83: =F23+F43+F63 -> -2865000 | G83: =E83+F83 -> 2115000
B85: Variance $ | C85: =C81-C83 -> 1834026.6 | D85: =D81-D83 -> -911426.94 | E85: =E81-E83 -> 922599.61 | F85: =F81-F83 -> -321590.94 | G85: =G81-G83 -> 601008.67
B87: Forecast Commentary
A88: # | B88: The group full-year outlook strengthens: net income of ~$2.72M vs an annualized budget of $2.12M (+$0.60M), with NI margin improving from 17.8% (Apr–Jul actuals) to ~19.2% for the full year.
A89: # | B89: Business A and B extend their momentum, full-year NI outlooks of $840K and $1.89M, well ahead of annualized budgets ($630K / $1.26M).
A90: # | B90: Business C returns to monthly profit in December 2026: revenue growth outpaces cost growth, closing monthly NI from −$3.0K (Apr) to +$1.3K (Mar), though the full year still lands near breakeven (−$11K vs a $225K budget).
A91: # | B91: Watch the cost lines: the COGS and SG&A trends are extrapolated from four months that ran over budget if cost inflation (not volume) drove the overruns, this forecast is optimistic.

Sheet Week 3 Dashboard
P1: Month | Q1: Revenue | R1: Net Income
B2: WEEK 3 | PERFORMANCE DASHBOARD | P2: ='Week 2 Forecast'!B69 -> 46142 | Q2: ='Week 2 Forecast'!C69 -> 1020000 | R2: ='Week 2 Forecast'!G69 -> 176000 | S2: Business A | T2: ='Week 2 Forecast'!G21 -> 839033.48 | U2: ='Week 2 Forecast'!G23 -> 630000
B3: Group FP&A | YTD = Apr–Jul actuals | FY Outlook = 4 actual + 8 FORECAST.ETS months | P3: ='Week 2 Forecast'!B70 -> 46172 | Q3: ='Week 2 Forecast'!C70 -> 1047000 | R3: ='Week 2 Forecast'!G70 -> 183000 | S3: Business B | T3: ='Week 2 Forecast'!G41 -> 1887944.2 | U3: ='Week 2 Forecast'!G43 -> 1260000
P4: ='Week 2 Forecast'!B71 -> 46203 | Q4: ='Week 2 Forecast'!C71 -> 1086000 | R4: ='Week 2 Forecast'!G71 -> 195000 | S4: Business C | T4: ='Week 2 Forecast'!G61 -> -10968.995 | U4: ='Week 2 Forecast'!G63 -> 225000
B5: FY REVENUE OUTLOOK | E5: FY NET INCOME OUTLOOK | H5: NI MARGIN OUTLOOK | K5: YTD NI VARIANCE | P5: ='Week 2 Forecast'!B72 -> 46233 | Q5: ='Week 2 Forecast'!C72 -> 1105000 | R5: ='Week 2 Forecast'!G72 -> 203000 | S5: Group | T5: ='Week 2 Forecast'!G81 -> 2716008.7 | U5: ='Week 2 Forecast'!G83 -> 2115000
B6: ='Week 2 Forecast'!C81 -> 14164027 | E6: ='Week 2 Forecast'!G81 -> 2716008.7 | H6: ='Week 2 Forecast'!G81/'Week 2 Forecast'!C81 -> 0.19175399 | K6: ='Group Consolidation'!M13 -> 52000 | P6: ='Week 2 Forecast'!B73 -> 46264 | Q6: ='Week 2 Forecast'!C73 -> 1136738.5 | R6: ='Week 2 Forecast'!G73 -> 212539.44
P7: ='Week 2 Forecast'!B74 -> 46295 | Q7: ='Week 2 Forecast'!C74 -> 1165884.2 | R7: ='Week 2 Forecast'!G74 -> 221823.55
B8: ="vs budget "&TEXT('Week 2 Forecast'!C85/'Week 2 Forecast'!C83,"+0.0%;-0.0%")&" ("&TEXT('Week 2 Forecast'!C85/1000,"+#,##0;(#,##0)")&"K)" -> vs budget +14.9% (+1,834K) | E8: ="vs budget "&TEXT('Week 2 Forecast'!G85/'Week 2 Forecast'!G83,"+0.0%;-0.0%")&" ("&TEXT('Week 2 Forecast'!G85/1000,"+#,##0;(#,##0)")&"K)" -> vs budget +28.4% (+601K) | H8: ="vs YTD margin "&TEXT('Group Consolidation'!J13/'Group Consolidation'!J9,"0.0%") -> vs YTD margin 17.8% | K8: ="Actual "&TEXT('Group Consolidation'!J13,"#,##0")&" vs budget "&TEXT('Group Consolidation'!K13,"#,##0") -> Actual 7,57,000 vs budget 7,05,000 | P8: ='Week 2 Forecast'!B75 -> 46325 | Q8: ='Week 2 Forecast'!C75 -> 1195030 | R8: ='Week 2 Forecast'!G75 -> 231107.67
P9: ='Week 2 Forecast'!B76 -> 46356 | Q9: ='Week 2 Forecast'!C76 -> 1224175.7 | R9: ='Week 2 Forecast'!G76 -> 240391.79
P10: ='Week 2 Forecast'!B77 -> 46386 | Q10: ='Week 2 Forecast'!C77 -> 1253321.5 | R10: ='Week 2 Forecast'!G77 -> 249675.91
B11: UNIT PERFORMANCE — NET INCOME | P11: ='Week 2 Forecast'!B78 -> 46417 | Q11: ='Week 2 Forecast'!C78 -> 1282467.2 | R11: ='Week 2 Forecast'!G78 -> 258960.03
B12: Unit | C12: YTD NI Actual | D12: FY NI Outlook | E12: FY NI Budget | F12: Variance $ | G12: Status | P12: ='Week 2 Forecast'!B79 -> 46446 | Q12: ='Week 2 Forecast'!C79 -> 1309732.6 | R12: ='Week 2 Forecast'!G79 -> 267645.17
B13: Business A | C13: =SUM('Week 2 Forecast'!G9:G12) -> 217000 | D13: ='Week 2 Forecast'!G21 -> 839033.48 | E13: ='Week 2 Forecast'!G23 -> 630000 | F13: =D13-E13 -> 209033.48 | G13: =IF(F13>=0,"Favorable","Unfavorable") -> Favorable | P13: ='Week 2 Forecast'!B80 -> 46474 | Q13: ='Week 2 Forecast'!C80 -> 1338676.9 | R13: ='Week 2 Forecast'!G80 -> 276865.11
B14: Business B | C14: =SUM('Week 2 Forecast'!G29:G32) -> 550000 | D14: ='Week 2 Forecast'!G41 -> 1887944.2 | E14: ='Week 2 Forecast'!G43 -> 1260000 | F14: =D14-E14 -> 627944.19 | G14: =IF(F14>=0,"Favorable","Unfavorable") -> Favorable
B15: Business C | C15: =SUM('Week 2 Forecast'!G49:G52) -> -10000 | D15: ='Week 2 Forecast'!G61 -> -10968.995 | E15: ='Week 2 Forecast'!G63 -> 225000 | F15: =D15-E15 -> -235968.99 | G15: =IF(F15>=0,"Favorable","Unfavorable") -> Unfavorable
B16: Group | C16: ='Group Consolidation'!J13 -> 757000 | D16: ='Week 2 Forecast'!G81 -> 2716008.7 | E16: ='Week 2 Forecast'!G83 -> 2115000 | F16: =D16-E16 -> 601008.67 | G16: =IF(F16>=0,"Favorable","Unfavorable") -> Favorable
B18: GROUP MONTHLY TREND — REVENUE & NET INCOME | H18: FY NET INCOME — OUTLOOK VS BUDGET
B34: EXECUTIVE TAKEAWAYS
A35: # | B35: Group FY net income outlook is 2.72M vs 2.12M budget (+28%).
A36: # | B36: Business B is the largest upside driver at 1.89M FY NI, while Business A also remains above plan.
A37: # | B37: Business C improves through the forecast but remains below budget; validate its cost base and revenue assumptions before relying on the turnaround.
A38: # | B38: Group NI margin improves from 17.8% YTD to 19.2% FY outlook.
A39: # | B39: Key risk: COGS and SG&A were already unfavorable YTD, while the ETS forecast uses only four actual months and no seasonality.
